rustymonad/__init__.py
rustymonad/monad.py
rustymonad/option.py
rustymonad/py.typed
rustymonad/result.py
rustymonad/utils.py
RustyMonad-1.0.0.dist-info/LICENSE
RustyMonad-1.0.0.dist-info/METADATA
RustyMonad-1.0.0.dist-info/WHEEL
RustyMonad-1.0.0.dist-info/top_level.txt
RustyMonad-1.0.0.dist-info/RECORD
