Metadata-Version: 2.1
Name: RustyMonad
Version: 1.0.0
Summary: Rust-style Monad utils for Python
Author: AkiSun
License: MIT License
Project-URL: Homepage, https://github.com/AkiSun/rustymonad
Project-URL: Issues, https://github.com/AkiSun/rustymonad/issues
Keywords: monad,functional
Classifier: Development Status :: 4 - Beta
Classifier: Programming Language :: Python :: 3.10
Classifier: License :: OSI Approved :: MIT License
Classifier: Operating System :: OS Independent
Requires-Python: >=3.10
License-File: LICENSE
